LICENSE
MANIFEST.in
README.md
setup.py
doc/source/arrays.rst
doc/source/backend.rst
doc/source/class.rst
doc/source/conf.py
doc/source/core.rst
doc/source/importers.rst
doc/source/index.rst
doc/source/preprocess.rst
doc/source/sphericalharm.rst
doc/source/submods.rst
doc/source/_static/demo_hfss_1.png
doc/source/_static/demo_hfss_2.png
doc/source/_static/demo_hfss_3.png
doc/source/_static/demo_operfreq.png
eadf/__init__.py
eadf/arrays.py
eadf/auxiliary.py
eadf/backend.py
eadf/core.py
eadf/eadf.py
eadf/importers.py
eadf/preprocess.py
eadf/sphericalharm.py
eadf.egg-info/PKG-INFO
eadf.egg-info/SOURCES.txt
eadf.egg-info/dependency_links.txt
eadf.egg-info/requires.txt
eadf.egg-info/top_level.txt
test/test_arrays.py
test/test_auxiliary.py
test/test_core.py
test/test_eadf.py
test/test_importers.py
test/test_preprocess.py
test/test_sphericalharm.py