Metadata-Version: 2.1
Name: eadf
Version: 0.5
Summary: Effective Aperture Distribution Function
Home-page: https://eadf.readthedocs.io/en/latest/
Author: EMS Group, TU Ilmenau, 2020
Author-email: sebastian.semper@tu-ilmenau.de
License: Apache Software License
Keywords: signal processing,array processing
Platform: UNKNOWN
Classifier: Intended Audience :: Science/Research
Classifier: License :: OSI Approved :: Apache Software License
Classifier: Operating System :: POSIX :: Linux
